<annotation>
  <folder>images</folder>
  <filename>70.jpg</filename>
  <size>
    <width>768</width>
    <height>1057</height>
    <depth>3</depth>
  </size>
  <segmented>0</segmented>
  <object>
    <name>signature</name>
    <pose>center</pose>
    <truncated>1</truncated>
    <difficult>0</difficult>
    <bndbox>
      <xmin>466</xmin>
      <ymin>877</ymin>
      <xmax>594</xmax>
      <ymax>908</ymax>
    </bndbox>
  </object>
  <object>
    <name>signature</name>
    <pose>center</pose>
    <truncated>1</truncated>
    <difficult>0</difficult>
    <bndbox>
      <xmin>302</xmin>
      <ymin>920</ymin>
      <xmax>401</xmax>
      <ymax>947</ymax>
    </bndbox>
  </object>
  <object>
    <name>signature</name>
    <pose>center</pose>
    <truncated>1</truncated>
    <difficult>0</difficult>
    <bndbox>
      <xmin>116</xmin>
      <ymin>922</ymin>
      <xmax>208</xmax>
      <ymax>943</ymax>
    </bndbox>
  </object>
  <object>
    <name>text</name>
    <pose>center</pose>
    <truncated>1</truncated>
    <difficult>0</difficult>
    <bndbox>
      <xmin>250</xmin>
      <ymin>129</ymin>
      <xmax>500</xmax>
      <ymax>151</ymax>
    </bndbox>
  </object>
  <object>
    <name>text</name>
    <pose>center</pose>
    <truncated>1</truncated>
    <difficult>0</difficult>
    <bndbox>
      <xmin>409</xmin>
      <ymin>159</ymin>
      <xmax>515</xmax>
      <ymax>510</ymax>
    </bndbox>
  </object>
  <object>
    <name>text</name>
    <pose>center</pose>
    <truncated>1</truncated>
    <difficult>0</difficult>
    <bndbox>
      <xmin>117</xmin>
      <ymin>162</ymin>
      <xmax>245</xmax>
      <ymax>516</ymax>
    </bndbox>
  </object>
  <object>
    <name>text</name>
    <pose>center</pose>
    <truncated>1</truncated>
    <difficult>0</difficult>
    <bndbox>
      <xmin>267</xmin>
      <ymin>206</ymin>
      <xmax>456</xmax>
      <ymax>232</ymax>
    </bndbox>
  </object>
  <object>
    <name>text</name>
    <pose>center</pose>
    <truncated>1</truncated>
    <difficult>0</difficult>
    <bndbox>
      <xmin>268</xmin>
      <ymin>579</ymin>
      <xmax>458</xmax>
      <ymax>601</ymax>
    </bndbox>
  </object>
  <object>
    <name>text</name>
    <pose>center</pose>
    <truncated>1</truncated>
    <difficult>0</difficult>
    <bndbox>
      <xmin>130</xmin>
      <ymin>594</ymin>
      <xmax>228</xmax>
      <ymax>615</ymax>
    </bndbox>
  </object>
  <object>
    <name>text</name>
    <pose>center</pose>
    <truncated>1</truncated>
    <difficult>0</difficult>
    <bndbox>
      <xmin>141</xmin>
      <ymin>764</ymin>
      <xmax>601</xmax>
      <ymax>820</ymax>
    </bndbox>
  </object>
  <object>
    <name>text</name>
    <pose>center</pose>
    <truncated>1</truncated>
    <difficult>0</difficult>
    <bndbox>
      <xmin>114</xmin>
      <ymin>857</ymin>
      <xmax>377</xmax>
      <ymax>921</ymax>
    </bndbox>
  </object>
</annotation>
